LICENSE
MANIFEST.in
README.rst
setup.cfg
setup.py
pypack/package.py
pypack.importer.egg-info/PKG-INFO
pypack.importer.egg-info/SOURCES.txt
pypack.importer.egg-info/dependency_links.txt
pypack.importer.egg-info/entry_points.txt
pypack.importer.egg-info/top_level.txt
pypack/__pycache__/package.cpython-35.pyc
pypack/importer/Importer.py
pypack/importer/__init__.py
pypack/importer/__pycache__/Importer.cpython-35.pyc
pypack/importer/__pycache__/__init__.cpython-35.pyc