Metadata-Version: 1.2
Name: pypack.importer
Version: 0.0.6
Summary: Pypack importer package
Home-page: https://github.com/pypack/pypack.importer
Author: Giovanni Cardamone
Author-email: g.cardamone2@gmail.com
License: MIT
Keywords: PyPack
Platform: UNKNOWN
Requires-Python: >=3
